eotdl/__init__.py
eotdl/cli.py
eotdl/access/__init__.py
eotdl/access/download.py
eotdl/access/matches.py
eotdl/access/search.py
eotdl/access/airbus/__init__.py
eotdl/access/airbus/client.py
eotdl/access/airbus/parameters.py
eotdl/access/airbus/utils.py
eotdl/access/sentinelhub/__init__.py
eotdl/access/sentinelhub/client.py
eotdl/access/sentinelhub/evalscripts.py
eotdl/access/sentinelhub/parameters.py
eotdl/access/sentinelhub/utils.py
eotdl/auth/__init__.py
eotdl/auth/auth.py
eotdl/auth/errors.py
eotdl/auth/is_logged.py
eotdl/auth/logout.py
eotdl/commands/__init__.py
eotdl/commands/auth.py
eotdl/commands/datasets.py
eotdl/commands/models.py
eotdl/commands/pipelines.py
eotdl/commands/stac.py
eotdl/curation/__init__.py
eotdl/curation/stac/__init__.py
eotdl/curation/stac/api.py
eotdl/curation/stac/stac.py
eotdl/datasets/__init__.py
eotdl/datasets/ingest.py
eotdl/datasets/retrieve.py
eotdl/datasets/stage.py
eotdl/datasets/update.py
eotdl/fe/__init__.py
eotdl/fe/ingest.py
eotdl/fe/retrieve.py
eotdl/fe/stage.py
eotdl/fe/update.py
eotdl/fe/openeo/__init__.py
eotdl/fe/openeo/advanced_patch_extraction.py
eotdl/fe/openeo/basic_point_extraction.py
eotdl/fe/openeo/dataframe_utils.py
eotdl/fe/openeo/s3proxy_utils.py
eotdl/fe/openeo/spatial_utils.py
eotdl/fe/openeo/temporal_utils.py
eotdl/files/__init__.py
eotdl/files/get_file.py
eotdl/files/get_url.py
eotdl/files/ingest.bck
eotdl/files/ingest.py
eotdl/files/metadata.py
eotdl/models/__init__.py
eotdl/models/download.py
eotdl/models/ingest.py
eotdl/models/retrieve.py
eotdl/models/stage.py
eotdl/models/update.py
eotdl/repos/APIRepo.py
eotdl/repos/AuthAPIRepo.py
eotdl/repos/AuthRepo.py
eotdl/repos/DatasetsAPIRepo.py
eotdl/repos/FEAPIRepo.py
eotdl/repos/FilesAPIRepo.py
eotdl/repos/ModelsAPIRepo.py
eotdl/repos/STACAPIRepo.py
eotdl/repos/__init__.py
eotdl/shared/__init__.py
eotdl/shared/checksum.py
eotdl/tools/__init__.py
eotdl/tools/ais_labelling.py
eotdl/tools/geo_utils.py
eotdl/tools/metadata.py
eotdl/tools/paths.py
eotdl-2025.6.27.post2.dist-info/METADATA
eotdl-2025.6.27.post2.dist-info/WHEEL
eotdl-2025.6.27.post2.dist-info/entry_points.txt
eotdl-2025.6.27.post2.dist-info/RECORD
