Metadata-Version: 2.4
Name: eotdl
Version: 2025.6.27.post2
Summary: Earth Observation Training Data Lab
Author-email: earthpulse <it@earthpulse.es>
License-Expression: MIT
Requires-Python: >=3.12
Requires-Dist: geopandas>=1.0.1
Requires-Dist: pydantic>=2.11.1
Requires-Dist: pyjwt>=2.10.1
Requires-Dist: pystac>=1.12.2
Requires-Dist: python-frontmatter>=1.1.0
Requires-Dist: requests>=2.32.3
Requires-Dist: stac-geoparquet>=0.6.0
Requires-Dist: tqdm>=4.67.1
Requires-Dist: typer>=0.15.2
